hubm_admin_panel/Groups/__init__.py
hubm_admin_panel/Groups/master.py
hubm_admin_panel/User/CreatePolicies.py
hubm_admin_panel/User/CreateUser.py
hubm_admin_panel/User/User.py
hubm_admin_panel/User/UserExport.py
hubm_admin_panel/User/__init__.py
hubm_admin_panel/__init__.py
hubm_admin_panel/apl_style/__init__.py
hubm_admin_panel/apl_style/style.py
hubm_admin_panel/apl_style/widgetstyle/__init__.py
hubm_admin_panel/apl_style/widgetstyle/base.py
hubm_admin_panel/apl_style/widgetstyle/checkbox.py
hubm_admin_panel/apl_style/widgetstyle/combobox.py
hubm_admin_panel/apl_style/widgetstyle/constants.py
hubm_admin_panel/apl_style/widgetstyle/groupbox.py
hubm_admin_panel/apl_style/widgetstyle/headerview.py
hubm_admin_panel/apl_style/widgetstyle/lineedit.py
hubm_admin_panel/apl_style/widgetstyle/progressbar.py
hubm_admin_panel/apl_style/widgetstyle/pushbutton.py
hubm_admin_panel/apl_style/widgetstyle/radiobutton.py
hubm_admin_panel/apl_style/widgetstyle/scrollarea.py
hubm_admin_panel/apl_style/widgetstyle/scrollbar.py
hubm_admin_panel/apl_style/widgetstyle/slider.py
hubm_admin_panel/apl_style/widgetstyle/spinbox.py
hubm_admin_panel/apl_style/widgetstyle/splitter.py
hubm_admin_panel/apl_style/widgetstyle/tableview.py
hubm_admin_panel/apl_style/widgetstyle/tabwidget.py
hubm_admin_panel/apl_style/widgetstyle/tabwidget_titlebar.py
hubm_admin_panel/apl_style/widgetstyle/toolbar.py
hubm_admin_panel/apl_style/widgetstyle/treeview.py
hubm_admin_panel/apl_style/windowstyle2/__init__.py
hubm_admin_panel/apl_style/windowstyle2/buttons.py
hubm_admin_panel/apl_style/windowstyle2/constants.py
hubm_admin_panel/apl_style/windowstyle2/frame.py
hubm_admin_panel/build.py
hubm_admin_panel/main.py
hubm_admin_panel/ui/__init__.py
hubm_admin_panel/ui/convert.py
hubm_admin_panel/ui/ui_exception.py
hubm_admin_panel/ui/ui_exception.ui
hubm_admin_panel/ui/ui_launch.py
hubm_admin_panel/ui/ui_launch.ui
hubm_admin_panel/ui/ui_main.py
hubm_admin_panel/ui/ui_main.ui
hubm_admin_panel/ui/ui_new_policies.py
hubm_admin_panel-0.0.301.dist-info/METADATA
hubm_admin_panel-0.0.301.dist-info/WHEEL
hubm_admin_panel-0.0.301.dist-info/entry_points.txt
hubm_admin_panel-0.0.301.dist-info/RECORD
