Metadata-Version: 2.1
Name: hubm-admin-panel
Version: 0.0.301
Summary: 
Home-page: https://github.com/python-poetry/poetry
Author: PrintLine512
Author-email: paralet.games@gmail.com
Requires-Python: >=3.11,<3.12
Classifier: Programming Language :: Python :: 3
Classifier: Programming Language :: Python :: 3.11
Requires-Dist: openpyxl (>=3.1.5,<4.0.0)
Requires-Dist: pandas (>=2.2.3,<3.0.0)
Requires-Dist: pyqtdarktheme (>=2.1.0,<3.0.0)
Requires-Dist: pyside6 (>=6.8.0.1,<7.0.0.0)
Requires-Dist: requests (>=2.32.3,<3.0.0)
Requires-Dist: rich (>=13.9.2,<14.0.0)
Project-URL: Documentation, https://python-poetry.org/docs/
Project-URL: Repository, https://github.com/python-poetry/poetry
